Metadata-Version: 1.1
Name: ZabbixSender
Version: 0.2.7
Summary: Simple zabbix sender
Home-page: https://github.com/maksim77/zsender
Author: Maksim Syomochkin
Author-email: maksim77ster@gmail.com
License: Apache Software License
Keywords: zabbix sender monitoring
Platform: UNKNOWN
Classifier: Development Status :: 3 - Alpha
Classifier: License :: OSI Approved :: Apache Software License
Classifier: Programming Language :: Python :: 3
Classifier: Intended Audience :: System Administrators
Classifier: Topic :: System :: Monitoring
Classifier: Topic :: System :: Networking :: Monitoring
Classifier: Topic :: System :: Systems Administration
